utilities/__init__.py
utilities/array.py
utilities/binning.py
utilities/catalog.py
utilities/constant.py
utilities/coordinate.py
utilities/cosmology.py
utilities/halo_property.py
utilities/io.py
utilities/math.py
utilities/orbit.py
utilities/particle.py
utilities/plot.py
utilities/simulation.py
utilities_awetzel-1.0.3.dist-info/licenses/LICENSE.md
utilities_awetzel-1.0.3.dist-info/METADATA
utilities_awetzel-1.0.3.dist-info/WHEEL
utilities_awetzel-1.0.3.dist-info/top_level.txt
utilities_awetzel-1.0.3.dist-info/RECORD
