Metadata-Version: 2.4
Name: utilities_awetzel
Version: 1.0.3
Summary: utilities for Andrew Wetzel's packages
Author: Shea Garrison-Kimmel, Jenna Samuel, Nico Garavito-Camargo, Kyle Oman
Author-email: Andrew Wetzel <arwetzel@gmail.com>
Maintainer-email: Andrew Wetzel <arwetzel@gmail.com>
License: Copyright 2014-2024 by the authors.
Project-URL: Repository, https://bitbucket.org/awetzel/utilities/src/master/
Project-URL: Issues, https://bitbucket.org/awetzel/utilities/issues?status=new&status=open&status=submitted
Keywords: utilities,astronomy,astrophysics,cosmology,galaxies,stars,dark matter
Classifier: Programming Language :: Python :: 3
Classifier: License :: OSI Approved :: MIT License
Classifier: Topic :: Scientific/Engineering :: Astronomy
Classifier: Development Status :: 4 - Beta
Classifier: Operating System :: OS Independent
Requires-Python: >=3.10
License-File: LICENSE.md
Requires-Dist: numpy>=1.22.2
Requires-Dist: scipy>=1.13.1
Requires-Dist: h5py>=3.9
Requires-Dist: matplotlib>=3.8
Dynamic: license-file
